avirtech_lpi_project/__init__.py
avirtech_lpi_project/avirtech_lpi_project.py
avirtech_lpi_project-0.0.6.dist-info/METADATA
avirtech_lpi_project-0.0.6.dist-info/WHEEL
avirtech_lpi_project-0.0.6.dist-info/top_level.txt
avirtech_lpi_project-0.0.6.dist-info/RECORD
