Metadata-Version: 2.1
Name: avirtech-lpi-project
Version: 0.0.6
Summary: Avirtech Python Library to generate gap, weed, sugarcane detection
Home-page: https://github.com/danibablas
Author: Bagus.W, ILham.R, Dwieka, Marisa
Author-email: baguswijanrk@gmail.com, ilhamr.mohammad@gmail.com,
License: MIT
Platform: UNKNOWN
Classifier: Intended Audience :: Developers
Classifier: License :: OSI Approved :: MIT License
Classifier: Programming Language :: Python
Classifier: Programming Language :: Python :: 3
Classifier: Programming Language :: Python :: 3.6
Classifier: Programming Language :: Python :: 3.7
Classifier: Programming Language :: Python :: 3.8
Classifier: Programming Language :: Python :: 3.9
Classifier: Operating System :: OS Independent
Requires-Dist: simpledbf
Requires-Dist: openpyxl
Requires-Dist: excel2img
Requires-Dist: spdf
